pyp2rpm/__init__.py
pyp2rpm/archive.py
pyp2rpm/bin.py
pyp2rpm/convertor.py
pyp2rpm/dependency_convert.py
pyp2rpm/dependency_parser.py
pyp2rpm/exceptions.py
pyp2rpm/filters.py
pyp2rpm/logger.py
pyp2rpm/metadata_extractors.py
pyp2rpm/module_runners.py
pyp2rpm/name_convertor.py
pyp2rpm/package_data.py
pyp2rpm/package_getters.py
pyp2rpm/settings.py
pyp2rpm/utils.py
pyp2rpm/version.py
pyp2rpm/virtualenv.py
pyp2rpm/command/__init__.py
pyp2rpm/command/extract_dist.py
pyp2rpm/templates/epel6.spec
pyp2rpm/templates/epel7.spec
pyp2rpm/templates/fedora.spec
pyp2rpm/templates/macros.spec
pyp2rpm/templates/mageia.spec
pyp2rpm/templates/pld.spec
pyp2rpm-3.3.10.dist-info/LICENSE
pyp2rpm-3.3.10.dist-info/METADATA
pyp2rpm-3.3.10.dist-info/WHEEL
pyp2rpm-3.3.10.dist-info/entry_points.txt
pyp2rpm-3.3.10.dist-info/top_level.txt
pyp2rpm-3.3.10.dist-info/RECORD
