Metadata-Version: 2.1
Name: pyp2rpm
Version: 3.3.10
Summary: Convert Python packages to RPM SPECFILES
Home-page: https://github.com/fedora-python/pyp2rpm
Author: Bohuslav "Slavek" Kabrda, Robert Kuska, Michal Cyprian, Iryna Shcherbina
Author-email: bkabrda@redhat.com, rkuska@redhat.com, mcyprian@redhat.com, ishcherb@redhat.com
License: MIT
Keywords: pypi,rpm,spec,specfile,convert
Classifier: Development Status :: 4 - Beta
Classifier: Environment :: Console
Classifier: Intended Audience :: Developers
Classifier: Intended Audience :: System Administrators
Classifier: License :: OSI Approved :: MIT License
Classifier: Operating System :: POSIX :: Linux
Classifier: Programming Language :: Python
Classifier: Programming Language :: Python :: 3
Classifier: Topic :: Software Development :: Build Tools
Classifier: Topic :: System :: Software Distribution
Provides-Extra: venv metadata
Provides-Extra: sclize
License-File: LICENSE
